package com.androlua.util;

import java.io.File;
import java.io.FileInputStream;
import java.io.FileOutputStream;
import java.io.InputStream;
import java.io.OutputStream;
import java.io.PrintStream;
import java.util.Enumeration;
import java.util.logging.Logger;
import java.util.zip.ZipEntry;
import java.util.zip.ZipFile;
import java.util.zip.ZipOutputStream;

public class ZipUtil
{
  private static final Logger a = Logger.getLogger(ZipUtil.class.getName());
  private static final byte[] b = new byte[4096];

  // ERROR //
  private static void a(File paramFile, ZipOutputStream paramZipOutputStream, String paramString)
  {
    // Byte code:
    //   0: aload_0
    //   1: invokevirtual 40	java/io/File:isFile	()Z
    //   4: istore_3
    //   5: iconst_0
    //   6: istore 4
    //   8: iload_3
    //   9: ifeq +213 -> 222
    //   12: aconst_null
    //   13: astore 7
    //   15: new 42	java/io/BufferedInputStream
    //   18: dup
    //   19: new 44	java/io/FileInputStream
    //   22: dup
    //   23: aload_0
    //   24: invokespecial 47	java/io/FileInputStream:<init>	(Ljava/io/File;)V
    //   27: getstatic 26	com/androlua/util/ZipUtil:b	[B
    //   30: arraylength
    //   31: invokespecial 50	java/io/BufferedInputStream:<init>	(Ljava/io/InputStream;I)V
    //   34: astore 8
    //   36: aload_0
    //   37: invokevirtual 53	java/io/File:getAbsolutePath	()Ljava/lang/String;
    //   40: aload_2
    //   41: invokevirtual 59	java/lang/String:indexOf	(Ljava/lang/String;)I
    //   44: istore 14
    //   46: aload_0
    //   47: invokevirtual 53	java/io/File:getAbsolutePath	()Ljava/lang/String;
    //   50: iload 14
    //   52: invokevirtual 63	java/lang/String:substring	(I)Ljava/lang/String;
    //   55: astore 15
    //   57: getstatic 69	java/lang/System:out	Ljava/io/PrintStream;
    //   60: aload 15
    //   62: invokevirtual 75	java/io/PrintStream:println	(Ljava/lang/String;)V
    //   65: aload_1
    //   66: new 77	java/util/zip/ZipEntry
    //   69: dup
    //   70: aload 15
    //   72: invokespecial 79	java/util/zip/ZipEntry:<init>	(Ljava/lang/String;)V
    //   75: invokevirtual 85	java/util/zip/ZipOutputStream:putNextEntry	(Ljava/util/zip/ZipEntry;)V
    //   78: aload 8
    //   80: getstatic 26	com/androlua/util/ZipUtil:b	[B
    //   83: iconst_0
    //   84: getstatic 26	com/androlua/util/ZipUtil:b	[B
    //   87: arraylength
    //   88: invokevirtual 89	java/io/BufferedInputStream:read	([BII)I
    //   91: istore 16
    //   93: iload 16
    //   95: iconst_m1
    //   96: if_icmpeq +16 -> 112
    //   99: aload_1
    //   100: getstatic 26	com/androlua/util/ZipUtil:b	[B
    //   103: iconst_0
    //   104: iload 16
    //   106: invokevirtual 93	java/util/zip/ZipOutputStream:write	([BII)V
    //   109: goto -31 -> 78
    //   112: aload 8
    //   114: ifnull +160 -> 274
    //   117: aload 8
    //   119: invokevirtual 96	java/io/BufferedInputStream:close	()V
    //   122: return
    //   123: astore 11
    //   125: goto +74 -> 199
    //   128: astore 13
    //   130: aload 8
    //   132: astore 7
    //   134: goto +23 -> 157
    //   137: astore 9
    //   139: aload 8
    //   141: astore 7
    //   143: goto +32 -> 175
    //   146: astore 11
    //   148: aload 7
    //   150: astore 8
    //   152: goto +47 -> 199
    //   155: astore 13
    //   157: aload 13
    //   159: invokestatic 101	com/a/a/a/a/a/a/a:a	(Ljava/lang/Throwable;)V
    //   162: aload 7
    //   164: ifnull +110 -> 274
    //   167: aload 7
    //   169: invokevirtual 96	java/io/BufferedInputStream:close	()V
    //   172: return
    //   173: astore 9
    //   175: aload 9
    //   177: invokestatic 101	com/a/a/a/a/a/a/a:a	(Ljava/lang/Throwable;)V
    //   180: aload 7
    //   182: ifnull +92 -> 274
    //   185: aload 7
    //   187: invokevirtual 96	java/io/BufferedInputStream:close	()V
    //   190: return
    //   191: astore 10
    //   193: aload 10
    //   195: invokestatic 101	com/a/a/a/a/a/a/a:a	(Ljava/lang/Throwable;)V
    //   198: return
    //   199: aload 8
    //   201: ifnull +18 -> 219
    //   204: aload 8
    //   206: invokevirtual 96	java/io/BufferedInputStream:close	()V
    //   209: goto +10 -> 219
    //   212: astore 12
    //   214: aload 12
    //   216: invokestatic 101	com/a/a/a/a/a/a/a:a	(Ljava/lang/Throwable;)V
    //   219: aload 11
    //   221: athrow
    //   222: aload_0
    //   223: invokevirtual 104	java/io/File:isDirectory	()Z
    //   226: ifeq +48 -> 274
    //   229: aload_0
    //   230: invokevirtual 108	java/io/File:listFiles	()[Ljava/io/File;
    //   233: astore 5
    //   235: aload 5
    //   237: ifnull +37 -> 274
    //   240: aload 5
    //   242: arraylength
    //   243: ifle +31 -> 274
    //   246: aload 5
    //   248: arraylength
    //   249: istore 6
    //   251: iload 4
    //   253: iload 6
    //   255: if_icmpge +19 -> 274
    //   258: aload 5
    //   260: iload 4
    //   262: aaload
    //   263: aload_1
    //   264: aload_2
    //   265: invokestatic 110	com/androlua/util/ZipUtil:a	(Ljava/io/File;Ljava/util/zip/ZipOutputStream;Ljava/lang/String;)V
    //   268: iinc 4 1
    //   271: goto -20 -> 251
    //   274: return
    //
    // Exception table:
    //   from	to	target	type
    //   36	78	123	finally
    //   78	93	123	finally
    //   99	109	123	finally
    //   36	78	128	java/io/IOException
    //   78	93	128	java/io/IOException
    //   99	109	128	java/io/IOException
    //   36	78	137	java/io/FileNotFoundException
    //   78	93	137	java/io/FileNotFoundException
    //   99	109	137	java/io/FileNotFoundException
    //   15	36	146	finally
    //   157	162	146	finally
    //   175	180	146	finally
    //   15	36	155	java/io/IOException
    //   15	36	173	java/io/FileNotFoundException
    //   117	122	191	java/io/IOException
    //   167	172	191	java/io/IOException
    //   185	190	191	java/io/IOException
    //   204	209	212	java/io/IOException
  }

  public static void append(String paramString1, String paramString2)
  {
    ZipFile localZipFile = new ZipFile(paramString1);
    ZipOutputStream localZipOutputStream = new ZipOutputStream(new FileOutputStream(paramString1));
    Enumeration localEnumeration = localZipFile.entries();
    while (localEnumeration.hasMoreElements())
    {
      ZipEntry localZipEntry2 = (ZipEntry)localEnumeration.nextElement();
      PrintStream localPrintStream2 = System.out;
      StringBuilder localStringBuilder2 = new StringBuilder();
      localStringBuilder2.append("copy: ");
      localStringBuilder2.append(localZipEntry2.getName());
      localPrintStream2.println(localStringBuilder2.toString());
      localZipOutputStream.putNextEntry(localZipEntry2);
      if (!localZipEntry2.isDirectory())
        copy(localZipFile.getInputStream(localZipEntry2), localZipOutputStream);
      localZipOutputStream.closeEntry();
    }
    ZipEntry localZipEntry1 = new ZipEntry(paramString2);
    PrintStream localPrintStream1 = System.out;
    StringBuilder localStringBuilder1 = new StringBuilder();
    localStringBuilder1.append("append: ");
    localStringBuilder1.append(localZipEntry1.getName());
    localPrintStream1.println(localStringBuilder1.toString());
    localZipOutputStream.putNextEntry(localZipEntry1);
    copy(new FileInputStream(new File(paramString2)), localZipOutputStream);
    localZipOutputStream.closeEntry();
    localZipFile.close();
    localZipOutputStream.close();
  }

  public static void copy(InputStream paramInputStream, OutputStream paramOutputStream)
  {
    while (true)
    {
      int i = paramInputStream.read(b);
      if (i == -1)
        break;
      paramOutputStream.write(b, 0, i);
    }
  }

  // ERROR //
  public static boolean unzip(File paramFile, String paramString)
  {
    // Byte code:
    //   0: aload_0
    //   1: invokevirtual 176	java/io/File:exists	()Z
    //   4: ifne +47 -> 51
    //   7: getstatic 24	com/androlua/util/ZipUtil:a	Ljava/util/logging/Logger;
    //   10: astore 31
    //   12: new 136	java/lang/StringBuilder
    //   15: dup
    //   16: invokespecial 137	java/lang/StringBuilder:<init>	()V
    //   19: astore 32
    //   21: aload 32
    //   23: aload_0
    //   24: invokevirtual 177	java/io/File:getName	()Ljava/lang/String;
    //   27: invokevirtual 142	java/lang/StringBuilder:append	(Ljava/lang/String;)Ljava/lang/StringBuilder;
    //   30: pop
    //   31: aload 32
    //   33: ldc 179
    //   35: invokevirtual 142	java/lang/StringBuilder:append	(Ljava/lang/String;)Ljava/lang/StringBuilder;
    //   38: pop
    //   39: aload 31
    //   41: aload 32
    //   43: invokevirtual 146	java/lang/StringBuilder:toString	()Ljava/lang/String;
    //   46: invokevirtual 182	java/util/logging/Logger:info	(Ljava/lang/String;)V
    //   49: iconst_0
    //   50: ireturn
    //   51: new 36	java/io/File
    //   54: dup
    //   55: aload_1
    //   56: invokespecial 161	java/io/File:<init>	(Ljava/lang/String;)V
    //   59: astore_2
    //   60: aload_2
    //   61: invokevirtual 176	java/io/File:exists	()Z
    //   64: ifne +54 -> 118
    //   67: aload_2
    //   68: invokevirtual 185	java/io/File:mkdirs	()Z
    //   71: ifne +47 -> 118
    //   74: getstatic 24	com/androlua/util/ZipUtil:a	Ljava/util/logging/Logger;
    //   77: astore 27
    //   79: new 136	java/lang/StringBuilder
    //   82: dup
    //   83: invokespecial 137	java/lang/StringBuilder:<init>	()V
    //   86: astore 28
    //   88: aload 28
    //   90: ldc 187
    //   92: invokevirtual 142	java/lang/StringBuilder:append	(Ljava/lang/String;)Ljava/lang/StringBuilder;
    //   95: pop
    //   96: aload 28
    //   98: aload_2
    //   99: invokevirtual 177	java/io/File:getName	()Ljava/lang/String;
    //   102: invokevirtual 142	java/lang/StringBuilder:append	(Ljava/lang/String;)Ljava/lang/StringBuilder;
    //   105: pop
    //   106: aload 27
    //   108: aload 28
    //   110: invokevirtual 146	java/lang/StringBuilder:toString	()Ljava/lang/String;
    //   113: invokevirtual 182	java/util/logging/Logger:info	(Ljava/lang/String;)V
    //   116: iconst_0
    //   117: ireturn
    //   118: aconst_null
    //   119: astore_3
    //   120: getstatic 24	com/androlua/util/ZipUtil:a	Ljava/util/logging/Logger;
    //   123: ldc 189
    //   125: invokevirtual 182	java/util/logging/Logger:info	(Ljava/lang/String;)V
    //   128: new 191	java/util/zip/ZipInputStream
    //   131: dup
    //   132: new 42	java/io/BufferedInputStream
    //   135: dup
    //   136: new 193	java/util/zip/CheckedInputStream
    //   139: dup
    //   140: new 44	java/io/FileInputStream
    //   143: dup
    //   144: aload_0
    //   145: invokespecial 47	java/io/FileInputStream:<init>	(Ljava/io/File;)V
    //   148: new 195	java/util/zip/Adler32
    //   151: dup
    //   152: invokespecial 196	java/util/zip/Adler32:<init>	()V
    //   155: invokespecial 199	java/util/zip/CheckedInputStream:<init>	(Ljava/io/InputStream;Ljava/util/zip/Checksum;)V
    //   158: invokespecial 202	java/io/BufferedInputStream:<init>	(Ljava/io/InputStream;)V
    //   161: invokespecial 203	java/util/zip/ZipInputStream:<init>	(Ljava/io/InputStream;)V
    //   164: astore 4
    //   166: aload 4
    //   168: invokevirtual 207	java/util/zip/ZipInputStream:getNextEntry	()Ljava/util/zip/ZipEntry;
    //   171: astore 13
    //   173: aload 13
    //   175: ifnull +206 -> 381
    //   178: aload 13
    //   180: invokevirtual 143	java/util/zip/ZipEntry:getName	()Ljava/lang/String;
    //   183: astore 14
    //   185: new 136	java/lang/StringBuilder
    //   188: dup
    //   189: invokespecial 137	java/lang/StringBuilder:<init>	()V
    //   192: astore 15
    //   194: aload 15
    //   196: aload_1
    //   197: invokevirtual 142	java/lang/StringBuilder:append	(Ljava/lang/String;)Ljava/lang/StringBuilder;
    //   200: pop
    //   201: aload 15
    //   203: ldc 209
    //   205: invokevirtual 142	java/lang/StringBuilder:append	(Ljava/lang/String;)Ljava/lang/StringBuilder;
    //   208: pop
    //   209: aload 15
    //   211: aload 14
    //   213: invokevirtual 142	java/lang/StringBuilder:append	(Ljava/lang/String;)Ljava/lang/StringBuilder;
    //   216: pop
    //   217: aload 15
    //   219: invokevirtual 146	java/lang/StringBuilder:toString	()Ljava/lang/String;
    //   222: astore 19
    //   224: getstatic 69	java/lang/System:out	Ljava/io/PrintStream;
    //   227: aload 19
    //   229: invokevirtual 75	java/io/PrintStream:println	(Ljava/lang/String;)V
    //   232: new 36	java/io/File
    //   235: dup
    //   236: aload 19
    //   238: invokespecial 161	java/io/File:<init>	(Ljava/lang/String;)V
    //   241: invokevirtual 213	java/io/File:getParentFile	()Ljava/io/File;
    //   244: astore 20
    //   246: aload 20
    //   248: invokevirtual 176	java/io/File:exists	()Z
    //   251: ifne +60 -> 311
    //   254: aload 20
    //   256: invokevirtual 185	java/io/File:mkdirs	()Z
    //   259: ifne +52 -> 311
    //   262: new 136	java/lang/StringBuilder
    //   265: dup
    //   266: invokespecial 137	java/lang/StringBuilder:<init>	()V
    //   269: astore 23
    //   271: aload 23
    //   273: ldc 215
    //   275: invokevirtual 142	java/lang/StringBuilder:append	(Ljava/lang/String;)Ljava/lang/StringBuilder;
    //   278: pop
    //   279: aload 23
    //   281: aload 20
    //   283: invokevirtual 177	java/io/File:getName	()Ljava/lang/String;
    //   286: invokevirtual 142	java/lang/StringBuilder:append	(Ljava/lang/String;)Ljava/lang/StringBuilder;
    //   289: pop
    //   290: aload 23
    //   292: ldc 217
    //   294: invokevirtual 142	java/lang/StringBuilder:append	(Ljava/lang/String;)Ljava/lang/StringBuilder;
    //   297: pop
    //   298: new 219	java/lang/RuntimeException
    //   301: dup
    //   302: aload 23
    //   304: invokevirtual 146	java/lang/StringBuilder:toString	()Ljava/lang/String;
    //   307: invokespecial 220	java/lang/RuntimeException:<init>	(Ljava/lang/String;)V
    //   310: athrow
    //   311: new 222	java/io/BufferedOutputStream
    //   314: dup
    //   315: new 117	java/io/FileOutputStream
    //   318: dup
    //   319: aload 19
    //   321: invokespecial 118	java/io/FileOutputStream:<init>	(Ljava/lang/String;)V
    //   324: getstatic 26	com/androlua/util/ZipUtil:b	[B
    //   327: arraylength
    //   328: invokespecial 225	java/io/BufferedOutputStream:<init>	(Ljava/io/OutputStream;I)V
    //   331: astore 21
    //   333: aload 4
    //   335: getstatic 26	com/androlua/util/ZipUtil:b	[B
    //   338: iconst_0
    //   339: getstatic 26	com/androlua/util/ZipUtil:b	[B
    //   342: arraylength
    //   343: invokevirtual 226	java/util/zip/ZipInputStream:read	([BII)I
    //   346: istore 22
    //   348: iload 22
    //   350: iconst_m1
    //   351: if_icmpeq +17 -> 368
    //   354: aload 21
    //   356: getstatic 26	com/androlua/util/ZipUtil:b	[B
    //   359: iconst_0
    //   360: iload 22
    //   362: invokevirtual 227	java/io/BufferedOutputStream:write	([BII)V
    //   365: goto -32 -> 333
    //   368: aload 21
    //   370: invokevirtual 230	java/io/BufferedOutputStream:flush	()V
    //   373: aload 21
    //   375: invokevirtual 231	java/io/BufferedOutputStream:close	()V
    //   378: goto -212 -> 166
    //   381: iconst_1
    //   382: istore 6
    //   384: aload 4
    //   386: ifnull +92 -> 478
    //   389: aload 4
    //   391: invokevirtual 232	java/util/zip/ZipInputStream:close	()V
    //   394: goto +84 -> 478
    //   397: astore 9
    //   399: aload 9
    //   401: invokestatic 101	com/a/a/a/a/a/a/a:a	(Ljava/lang/Throwable;)V
    //   404: goto +74 -> 478
    //   407: astore 10
    //   409: goto +105 -> 514
    //   412: astore 12
    //   414: aload 4
    //   416: astore_3
    //   417: goto +21 -> 438
    //   420: astore 5
    //   422: aload 4
    //   424: astore_3
    //   425: goto +37 -> 462
    //   428: astore 10
    //   430: aload_3
    //   431: astore 4
    //   433: goto +81 -> 514
    //   436: astore 12
    //   438: aload 12
    //   440: invokestatic 101	com/a/a/a/a/a/a/a:a	(Ljava/lang/Throwable;)V
    //   443: iconst_0
    //   444: istore 6
    //   446: aload_3
    //   447: ifnull +31 -> 478
    //   450: aload_3
    //   451: invokevirtual 232	java/util/zip/ZipInputStream:close	()V
    //   454: iconst_0
    //   455: istore 6
    //   457: goto +21 -> 478
    //   460: astore 5
    //   462: aload 5
    //   464: invokestatic 101	com/a/a/a/a/a/a/a:a	(Ljava/lang/Throwable;)V
    //   467: iconst_0
    //   468: istore 6
    //   470: aload_3
    //   471: ifnull +7 -> 478
    //   474: aload_3
    //   475: invokevirtual 232	java/util/zip/ZipInputStream:close	()V
    //   478: iload 6
    //   480: ifeq +22 -> 502
    //   483: getstatic 24	com/androlua/util/ZipUtil:a	Ljava/util/logging/Logger;
    //   486: astore 7
    //   488: ldc 234
    //   490: astore 8
    //   492: aload 7
    //   494: aload 8
    //   496: invokevirtual 182	java/util/logging/Logger:info	(Ljava/lang/String;)V
    //   499: iload 6
    //   501: ireturn
    //   502: getstatic 24	com/androlua/util/ZipUtil:a	Ljava/util/logging/Logger;
    //   505: astore 7
    //   507: ldc 236
    //   509: astore 8
    //   511: goto -19 -> 492
    //   514: aload 4
    //   516: ifnull +18 -> 534
    //   519: aload 4
    //   521: invokevirtual 232	java/util/zip/ZipInputStream:close	()V
    //   524: goto +10 -> 534
    //   527: astore 11
    //   529: aload 11
    //   531: invokestatic 101	com/a/a/a/a/a/a/a:a	(Ljava/lang/Throwable;)V
    //   534: aload 10
    //   536: athrow
    //
    // Exception table:
    //   from	to	target	type
    //   389	394	397	java/io/IOException
    //   450	454	397	java/io/IOException
    //   474	478	397	java/io/IOException
    //   166	173	407	finally
    //   178	311	407	finally
    //   311	333	407	finally
    //   333	348	407	finally
    //   354	365	407	finally
    //   368	378	407	finally
    //   166	173	412	java/io/IOException
    //   178	311	412	java/io/IOException
    //   311	333	412	java/io/IOException
    //   333	348	412	java/io/IOException
    //   354	365	412	java/io/IOException
    //   368	378	412	java/io/IOException
    //   166	173	420	java/io/FileNotFoundException
    //   178	311	420	java/io/FileNotFoundException
    //   311	333	420	java/io/FileNotFoundException
    //   333	348	420	java/io/FileNotFoundException
    //   354	365	420	java/io/FileNotFoundException
    //   368	378	420	java/io/FileNotFoundException
    //   128	166	428	finally
    //   438	443	428	finally
    //   462	467	428	finally
    //   128	166	436	java/io/IOException
    //   128	166	460	java/io/FileNotFoundException
    //   519	524	527	java/io/IOException
  }

  public static boolean unzip(String paramString1, String paramString2)
  {
    return unzip(new File(paramString1), paramString2);
  }

  // ERROR //
  public static boolean zip(String paramString1, String paramString2)
  {
    // Byte code:
    //   0: new 36	java/io/File
    //   3: dup
    //   4: aload_0
    //   5: invokespecial 161	java/io/File:<init>	(Ljava/lang/String;)V
    //   8: astore_2
    //   9: aload_2
    //   10: invokevirtual 176	java/io/File:exists	()Z
    //   13: ifne +48 -> 61
    //   16: getstatic 24	com/androlua/util/ZipUtil:a	Ljava/util/logging/Logger;
    //   19: astore 21
    //   21: new 136	java/lang/StringBuilder
    //   24: dup
    //   25: invokespecial 137	java/lang/StringBuilder:<init>	()V
    //   28: astore 22
    //   30: aload 22
    //   32: aload_0
    //   33: invokevirtual 142	java/lang/StringBuilder:append	(Ljava/lang/String;)Ljava/lang/StringBuilder;
    //   36: pop
    //   37: ldc 179
    //   39: astore 24
    //   41: aload 22
    //   43: aload 24
    //   45: invokevirtual 142	java/lang/StringBuilder:append	(Ljava/lang/String;)Ljava/lang/StringBuilder;
    //   48: pop
    //   49: aload 21
    //   51: aload 22
    //   53: invokevirtual 146	java/lang/StringBuilder:toString	()Ljava/lang/String;
    //   56: invokevirtual 182	java/util/logging/Logger:info	(Ljava/lang/String;)V
    //   59: iconst_0
    //   60: ireturn
    //   61: aload_2
    //   62: invokevirtual 104	java/io/File:isDirectory	()Z
    //   65: ifne +31 -> 96
    //   68: getstatic 24	com/androlua/util/ZipUtil:a	Ljava/util/logging/Logger;
    //   71: astore 21
    //   73: new 136	java/lang/StringBuilder
    //   76: dup
    //   77: invokespecial 137	java/lang/StringBuilder:<init>	()V
    //   80: astore 22
    //   82: aload 22
    //   84: aload_0
    //   85: invokevirtual 142	java/lang/StringBuilder:append	(Ljava/lang/String;)Ljava/lang/StringBuilder;
    //   88: pop
    //   89: ldc 242
    //   91: astore 24
    //   93: goto -52 -> 41
    //   96: new 136	java/lang/StringBuilder
    //   99: dup
    //   100: invokespecial 137	java/lang/StringBuilder:<init>	()V
    //   103: astore_3
    //   104: aload_3
    //   105: aload_1
    //   106: invokevirtual 142	java/lang/StringBuilder:append	(Ljava/lang/String;)Ljava/lang/StringBuilder;
    //   109: pop
    //   110: aload_3
    //   111: ldc 209
    //   113: invokevirtual 142	java/lang/StringBuilder:append	(Ljava/lang/String;)Ljava/lang/StringBuilder;
    //   116: pop
    //   117: aload_3
    //   118: aload_2
    //   119: invokevirtual 177	java/io/File:getName	()Ljava/lang/String;
    //   122: invokevirtual 142	java/lang/StringBuilder:append	(Ljava/lang/String;)Ljava/lang/StringBuilder;
    //   125: pop
    //   126: aload_3
    //   127: ldc 244
    //   129: invokevirtual 142	java/lang/StringBuilder:append	(Ljava/lang/String;)Ljava/lang/StringBuilder;
    //   132: pop
    //   133: new 36	java/io/File
    //   136: dup
    //   137: aload_3
    //   138: invokevirtual 146	java/lang/StringBuilder:toString	()Ljava/lang/String;
    //   141: invokespecial 161	java/io/File:<init>	(Ljava/lang/String;)V
    //   144: astore 8
    //   146: aload 8
    //   148: invokevirtual 176	java/io/File:exists	()Z
    //   151: ifeq +35 -> 186
    //   154: getstatic 24	com/androlua/util/ZipUtil:a	Ljava/util/logging/Logger;
    //   157: astore 21
    //   159: new 136	java/lang/StringBuilder
    //   162: dup
    //   163: invokespecial 137	java/lang/StringBuilder:<init>	()V
    //   166: astore 22
    //   168: aload 22
    //   170: aload 8
    //   172: invokevirtual 177	java/io/File:getName	()Ljava/lang/String;
    //   175: invokevirtual 142	java/lang/StringBuilder:append	(Ljava/lang/String;)Ljava/lang/StringBuilder;
    //   178: pop
    //   179: ldc 246
    //   181: astore 24
    //   183: goto -142 -> 41
    //   186: aload 8
    //   188: invokevirtual 213	java/io/File:getParentFile	()Ljava/io/File;
    //   191: invokevirtual 176	java/io/File:exists	()Z
    //   194: ifne +46 -> 240
    //   197: aload 8
    //   199: invokevirtual 213	java/io/File:getParentFile	()Ljava/io/File;
    //   202: invokevirtual 185	java/io/File:mkdirs	()Z
    //   205: ifne +35 -> 240
    //   208: getstatic 24	com/androlua/util/ZipUtil:a	Ljava/util/logging/Logger;
    //   211: astore 21
    //   213: new 136	java/lang/StringBuilder
    //   216: dup
    //   217: invokespecial 137	java/lang/StringBuilder:<init>	()V
    //   220: astore 22
    //   222: aload 22
    //   224: ldc 187
    //   226: invokevirtual 142	java/lang/StringBuilder:append	(Ljava/lang/String;)Ljava/lang/StringBuilder;
    //   229: pop
    //   230: aload 8
    //   232: invokevirtual 177	java/io/File:getName	()Ljava/lang/String;
    //   235: astore 24
    //   237: goto -196 -> 41
    //   240: getstatic 24	com/androlua/util/ZipUtil:a	Ljava/util/logging/Logger;
    //   243: ldc 248
    //   245: invokevirtual 182	java/util/logging/Logger:info	(Ljava/lang/String;)V
    //   248: aconst_null
    //   249: astore 9
    //   251: new 81	java/util/zip/ZipOutputStream
    //   254: dup
    //   255: new 222	java/io/BufferedOutputStream
    //   258: dup
    //   259: new 250	java/util/zip/CheckedOutputStream
    //   262: dup
    //   263: new 117	java/io/FileOutputStream
    //   266: dup
    //   267: aload 8
    //   269: invokespecial 251	java/io/FileOutputStream:<init>	(Ljava/io/File;)V
    //   272: new 195	java/util/zip/Adler32
    //   275: dup
    //   276: invokespecial 196	java/util/zip/Adler32:<init>	()V
    //   279: invokespecial 254	java/util/zip/CheckedOutputStream:<init>	(Ljava/io/OutputStream;Ljava/util/zip/Checksum;)V
    //   282: invokespecial 255	java/io/BufferedOutputStream:<init>	(Ljava/io/OutputStream;)V
    //   285: invokespecial 121	java/util/zip/ZipOutputStream:<init>	(Ljava/io/OutputStream;)V
    //   288: astore 10
    //   290: aload 10
    //   292: bipush 8
    //   294: invokevirtual 259	java/util/zip/ZipOutputStream:setMethod	(I)V
    //   297: aload_2
    //   298: aload 10
    //   300: aload_2
    //   301: invokevirtual 177	java/io/File:getName	()Ljava/lang/String;
    //   304: invokestatic 110	com/androlua/util/ZipUtil:a	(Ljava/io/File;Ljava/util/zip/ZipOutputStream;Ljava/lang/String;)V
    //   307: iconst_1
    //   308: istore 12
    //   310: aload 10
    //   312: ifnull +94 -> 406
    //   315: aload 10
    //   317: invokevirtual 158	java/util/zip/ZipOutputStream:closeEntry	()V
    //   320: goto +10 -> 330
    //   323: astore 20
    //   325: aload 20
    //   327: invokestatic 101	com/a/a/a/a/a/a/a:a	(Ljava/lang/Throwable;)V
    //   330: aload 10
    //   332: invokevirtual 163	java/util/zip/ZipOutputStream:close	()V
    //   335: goto +71 -> 406
    //   338: astore 16
    //   340: aload 16
    //   342: invokestatic 101	com/a/a/a/a/a/a/a:a	(Ljava/lang/Throwable;)V
    //   345: goto +61 -> 406
    //   348: astore 17
    //   350: aload 10
    //   352: astore 9
    //   354: goto +88 -> 442
    //   357: astore 11
    //   359: aload 10
    //   361: astore 9
    //   363: goto +10 -> 373
    //   366: astore 17
    //   368: goto +74 -> 442
    //   371: astore 11
    //   373: aload 11
    //   375: invokestatic 101	com/a/a/a/a/a/a/a:a	(Ljava/lang/Throwable;)V
    //   378: iconst_0
    //   379: istore 12
    //   381: aload 9
    //   383: ifnull +23 -> 406
    //   386: aload 9
    //   388: invokevirtual 158	java/util/zip/ZipOutputStream:closeEntry	()V
    //   391: goto +10 -> 401
    //   394: astore 15
    //   396: aload 15
    //   398: invokestatic 101	com/a/a/a/a/a/a/a:a	(Ljava/lang/Throwable;)V
    //   401: aload 9
    //   403: invokevirtual 163	java/util/zip/ZipOutputStream:close	()V
    //   406: iload 12
    //   408: ifeq +22 -> 430
    //   411: getstatic 24	com/androlua/util/ZipUtil:a	Ljava/util/logging/Logger;
    //   414: astore 13
    //   416: ldc 234
    //   418: astore 14
    //   420: aload 13
    //   422: aload 14
    //   424: invokevirtual 182	java/util/logging/Logger:info	(Ljava/lang/String;)V
    //   427: iload 12
    //   429: ireturn
    //   430: getstatic 24	com/androlua/util/ZipUtil:a	Ljava/util/logging/Logger;
    //   433: astore 13
    //   435: ldc 236
    //   437: astore 14
    //   439: goto -19 -> 420
    //   442: aload 9
    //   444: ifnull +33 -> 477
    //   447: aload 9
    //   449: invokevirtual 158	java/util/zip/ZipOutputStream:closeEntry	()V
    //   452: goto +10 -> 462
    //   455: astore 18
    //   457: aload 18
    //   459: invokestatic 101	com/a/a/a/a/a/a/a:a	(Ljava/lang/Throwable;)V
    //   462: aload 9
    //   464: invokevirtual 163	java/util/zip/ZipOutputStream:close	()V
    //   467: goto +10 -> 477
    //   470: astore 19
    //   472: aload 19
    //   474: invokestatic 101	com/a/a/a/a/a/a/a:a	(Ljava/lang/Throwable;)V
    //   477: aload 17
    //   479: athrow
    //
    // Exception table:
    //   from	to	target	type
    //   315	320	323	java/io/IOException
    //   330	335	338	java/io/IOException
    //   401	406	338	java/io/IOException
    //   290	307	348	finally
    //   290	307	357	java/io/FileNotFoundException
    //   251	290	366	finally
    //   373	378	366	finally
    //   251	290	371	java/io/FileNotFoundException
    //   386	391	394	java/io/IOException
    //   447	452	455	java/io/IOException
    //   462	467	470	java/io/IOException
  }
}

/* Location:           C:\Users\86186\Downloads\反编译工具包\01_反编译工具包\dex2jar-0.0.9.15\dex2jar-0.0.9.15\classes_dex2jar.jar
 * Qualified Name:     com.androlua.util.ZipUtil
 * JD-Core Version:    0.6.2
 */