package com.android.cglib.dx;

import com.android.cglib.dx.c.b.p;
import com.android.cglib.dx.c.b.r;
import com.android.cglib.dx.c.d.e;

public enum BinaryOp
{
  static
  {
    // Byte code:
    //   0: new 23	com/android/cglib/dx/BinaryOp$1
    //   3: dup
    //   4: ldc 24
    //   6: iconst_0
    //   7: invokespecial 28	com/android/cglib/dx/BinaryOp$1:<init>	(Ljava/lang/String;I)V
    //   10: putstatic 30	com/android/cglib/dx/BinaryOp:ADD	Lcom/android/cglib/dx/BinaryOp;
    //   13: new 32	com/android/cglib/dx/BinaryOp$2
    //   16: dup
    //   17: ldc 33
    //   19: iconst_1
    //   20: invokespecial 34	com/android/cglib/dx/BinaryOp$2:<init>	(Ljava/lang/String;I)V
    //   23: putstatic 36	com/android/cglib/dx/BinaryOp:SUBTRACT	Lcom/android/cglib/dx/BinaryOp;
    //   26: new 38	com/android/cglib/dx/BinaryOp$3
    //   29: dup
    //   30: ldc 39
    //   32: iconst_2
    //   33: invokespecial 40	com/android/cglib/dx/BinaryOp$3:<init>	(Ljava/lang/String;I)V
    //   36: putstatic 42	com/android/cglib/dx/BinaryOp:MULTIPLY	Lcom/android/cglib/dx/BinaryOp;
    //   39: new 44	com/android/cglib/dx/BinaryOp$4
    //   42: dup
    //   43: ldc 45
    //   45: iconst_3
    //   46: invokespecial 46	com/android/cglib/dx/BinaryOp$4:<init>	(Ljava/lang/String;I)V
    //   49: putstatic 48	com/android/cglib/dx/BinaryOp:DIVIDE	Lcom/android/cglib/dx/BinaryOp;
    //   52: new 50	com/android/cglib/dx/BinaryOp$5
    //   55: dup
    //   56: ldc 51
    //   58: iconst_4
    //   59: invokespecial 52	com/android/cglib/dx/BinaryOp$5:<init>	(Ljava/lang/String;I)V
    //   62: putstatic 54	com/android/cglib/dx/BinaryOp:REMAINDER	Lcom/android/cglib/dx/BinaryOp;
    //   65: new 56	com/android/cglib/dx/BinaryOp$6
    //   68: dup
    //   69: ldc 57
    //   71: iconst_5
    //   72: invokespecial 58	com/android/cglib/dx/BinaryOp$6:<init>	(Ljava/lang/String;I)V
    //   75: putstatic 60	com/android/cglib/dx/BinaryOp:AND	Lcom/android/cglib/dx/BinaryOp;
    //   78: new 62	com/android/cglib/dx/BinaryOp$7
    //   81: dup
    //   82: ldc 63
    //   84: bipush 6
    //   86: invokespecial 64	com/android/cglib/dx/BinaryOp$7:<init>	(Ljava/lang/String;I)V
    //   89: putstatic 66	com/android/cglib/dx/BinaryOp:OR	Lcom/android/cglib/dx/BinaryOp;
    //   92: new 68	com/android/cglib/dx/BinaryOp$8
    //   95: dup
    //   96: ldc 69
    //   98: bipush 7
    //   100: invokespecial 70	com/android/cglib/dx/BinaryOp$8:<init>	(Ljava/lang/String;I)V
    //   103: putstatic 72	com/android/cglib/dx/BinaryOp:XOR	Lcom/android/cglib/dx/BinaryOp;
    //   106: new 74	com/android/cglib/dx/BinaryOp$9
    //   109: dup
    //   110: ldc 75
    //   112: bipush 8
    //   114: invokespecial 76	com/android/cglib/dx/BinaryOp$9:<init>	(Ljava/lang/String;I)V
    //   117: putstatic 78	com/android/cglib/dx/BinaryOp:SHIFT_LEFT	Lcom/android/cglib/dx/BinaryOp;
    //   120: new 80	com/android/cglib/dx/BinaryOp$10
    //   123: dup
    //   124: ldc 81
    //   126: bipush 9
    //   128: invokespecial 82	com/android/cglib/dx/BinaryOp$10:<init>	(Ljava/lang/String;I)V
    //   131: putstatic 84	com/android/cglib/dx/BinaryOp:SHIFT_RIGHT	Lcom/android/cglib/dx/BinaryOp;
    //   134: new 86	com/android/cglib/dx/BinaryOp$11
    //   137: dup
    //   138: ldc 87
    //   140: bipush 10
    //   142: invokespecial 88	com/android/cglib/dx/BinaryOp$11:<init>	(Ljava/lang/String;I)V
    //   145: putstatic 90	com/android/cglib/dx/BinaryOp:UNSIGNED_SHIFT_RIGHT	Lcom/android/cglib/dx/BinaryOp;
    //   148: bipush 11
    //   150: anewarray 2	com/android/cglib/dx/BinaryOp
    //   153: astore_0
    //   154: aload_0
    //   155: iconst_0
    //   156: getstatic 30	com/android/cglib/dx/BinaryOp:ADD	Lcom/android/cglib/dx/BinaryOp;
    //   159: aastore
    //   160: aload_0
    //   161: iconst_1
    //   162: getstatic 36	com/android/cglib/dx/BinaryOp:SUBTRACT	Lcom/android/cglib/dx/BinaryOp;
    //   165: aastore
    //   166: aload_0
    //   167: iconst_2
    //   168: getstatic 42	com/android/cglib/dx/BinaryOp:MULTIPLY	Lcom/android/cglib/dx/BinaryOp;
    //   171: aastore
    //   172: aload_0
    //   173: iconst_3
    //   174: getstatic 48	com/android/cglib/dx/BinaryOp:DIVIDE	Lcom/android/cglib/dx/BinaryOp;
    //   177: aastore
    //   178: aload_0
    //   179: iconst_4
    //   180: getstatic 54	com/android/cglib/dx/BinaryOp:REMAINDER	Lcom/android/cglib/dx/BinaryOp;
    //   183: aastore
    //   184: aload_0
    //   185: iconst_5
    //   186: getstatic 60	com/android/cglib/dx/BinaryOp:AND	Lcom/android/cglib/dx/BinaryOp;
    //   189: aastore
    //   190: aload_0
    //   191: bipush 6
    //   193: getstatic 66	com/android/cglib/dx/BinaryOp:OR	Lcom/android/cglib/dx/BinaryOp;
    //   196: aastore
    //   197: aload_0
    //   198: bipush 7
    //   200: getstatic 72	com/android/cglib/dx/BinaryOp:XOR	Lcom/android/cglib/dx/BinaryOp;
    //   203: aastore
    //   204: aload_0
    //   205: bipush 8
    //   207: getstatic 78	com/android/cglib/dx/BinaryOp:SHIFT_LEFT	Lcom/android/cglib/dx/BinaryOp;
    //   210: aastore
    //   211: aload_0
    //   212: bipush 9
    //   214: getstatic 84	com/android/cglib/dx/BinaryOp:SHIFT_RIGHT	Lcom/android/cglib/dx/BinaryOp;
    //   217: aastore
    //   218: aload_0
    //   219: bipush 10
    //   221: getstatic 90	com/android/cglib/dx/BinaryOp:UNSIGNED_SHIFT_RIGHT	Lcom/android/cglib/dx/BinaryOp;
    //   224: aastore
    //   225: aload_0
    //   226: putstatic 92	com/android/cglib/dx/BinaryOp:$VALUES	[Lcom/android/cglib/dx/BinaryOp;
    //   229: return
  }

  abstract p rop(e parame);
}

/* Location:           C:\Users\86186\Downloads\反编译工具包\01_反编译工具包\dex2jar-0.0.9.15\dex2jar-0.0.9.15\classes_dex2jar.jar
 * Qualified Name:     com.android.cglib.dx.BinaryOp
 * JD-Core Version:    0.6.2
 */