package com.android.cglib.dx.b.a;

public enum a
{
  static
  {
    // Byte code:
    //   0: new 52	com/android/cglib/dx/b/a/a$1
    //   3: dup
    //   4: ldc 54
    //   6: iconst_0
    //   7: invokespecial 58	com/android/cglib/dx/b/a/a$1:<init>	(Ljava/lang/String;I)V
    //   10: putstatic 60	com/android/cglib/dx/b/a/a:a	Lcom/android/cglib/dx/b/a/a;
    //   13: new 62	com/android/cglib/dx/b/a/a$12
    //   16: dup
    //   17: ldc 64
    //   19: iconst_1
    //   20: invokespecial 65	com/android/cglib/dx/b/a/a$12:<init>	(Ljava/lang/String;I)V
    //   23: putstatic 67	com/android/cglib/dx/b/a/a:b	Lcom/android/cglib/dx/b/a/a;
    //   26: new 69	com/android/cglib/dx/b/a/a$23
    //   29: dup
    //   30: ldc 71
    //   32: iconst_2
    //   33: invokespecial 72	com/android/cglib/dx/b/a/a$23:<init>	(Ljava/lang/String;I)V
    //   36: putstatic 74	com/android/cglib/dx/b/a/a:c	Lcom/android/cglib/dx/b/a/a;
    //   39: new 76	com/android/cglib/dx/b/a/a$34
    //   42: dup
    //   43: ldc 78
    //   45: iconst_3
    //   46: invokespecial 79	com/android/cglib/dx/b/a/a$34:<init>	(Ljava/lang/String;I)V
    //   49: putstatic 81	com/android/cglib/dx/b/a/a:d	Lcom/android/cglib/dx/b/a/a;
    //   52: new 83	com/android/cglib/dx/b/a/a$36
    //   55: dup
    //   56: ldc 85
    //   58: iconst_4
    //   59: invokespecial 86	com/android/cglib/dx/b/a/a$36:<init>	(Ljava/lang/String;I)V
    //   62: putstatic 88	com/android/cglib/dx/b/a/a:e	Lcom/android/cglib/dx/b/a/a;
    //   65: new 90	com/android/cglib/dx/b/a/a$37
    //   68: dup
    //   69: ldc 92
    //   71: iconst_5
    //   72: invokespecial 93	com/android/cglib/dx/b/a/a$37:<init>	(Ljava/lang/String;I)V
    //   75: putstatic 95	com/android/cglib/dx/b/a/a:f	Lcom/android/cglib/dx/b/a/a;
    //   78: new 97	com/android/cglib/dx/b/a/a$38
    //   81: dup
    //   82: ldc 99
    //   84: bipush 6
    //   86: invokespecial 100	com/android/cglib/dx/b/a/a$38:<init>	(Ljava/lang/String;I)V
    //   89: putstatic 102	com/android/cglib/dx/b/a/a:g	Lcom/android/cglib/dx/b/a/a;
    //   92: new 104	com/android/cglib/dx/b/a/a$39
    //   95: dup
    //   96: ldc 106
    //   98: bipush 7
    //   100: invokespecial 107	com/android/cglib/dx/b/a/a$39:<init>	(Ljava/lang/String;I)V
    //   103: putstatic 109	com/android/cglib/dx/b/a/a:h	Lcom/android/cglib/dx/b/a/a;
    //   106: new 111	com/android/cglib/dx/b/a/a$40
    //   109: dup
    //   110: ldc 113
    //   112: bipush 8
    //   114: invokespecial 114	com/android/cglib/dx/b/a/a$40:<init>	(Ljava/lang/String;I)V
    //   117: putstatic 116	com/android/cglib/dx/b/a/a:i	Lcom/android/cglib/dx/b/a/a;
    //   120: new 118	com/android/cglib/dx/b/a/a$2
    //   123: dup
    //   124: ldc 120
    //   126: bipush 9
    //   128: invokespecial 121	com/android/cglib/dx/b/a/a$2:<init>	(Ljava/lang/String;I)V
    //   131: putstatic 123	com/android/cglib/dx/b/a/a:j	Lcom/android/cglib/dx/b/a/a;
    //   134: new 125	com/android/cglib/dx/b/a/a$3
    //   137: dup
    //   138: ldc 127
    //   140: bipush 10
    //   142: invokespecial 128	com/android/cglib/dx/b/a/a$3:<init>	(Ljava/lang/String;I)V
    //   145: putstatic 130	com/android/cglib/dx/b/a/a:k	Lcom/android/cglib/dx/b/a/a;
    //   148: new 132	com/android/cglib/dx/b/a/a$4
    //   151: dup
    //   152: ldc 134
    //   154: bipush 11
    //   156: invokespecial 135	com/android/cglib/dx/b/a/a$4:<init>	(Ljava/lang/String;I)V
    //   159: putstatic 137	com/android/cglib/dx/b/a/a:l	Lcom/android/cglib/dx/b/a/a;
    //   162: new 139	com/android/cglib/dx/b/a/a$5
    //   165: dup
    //   166: ldc 141
    //   168: bipush 12
    //   170: invokespecial 142	com/android/cglib/dx/b/a/a$5:<init>	(Ljava/lang/String;I)V
    //   173: putstatic 144	com/android/cglib/dx/b/a/a:m	Lcom/android/cglib/dx/b/a/a;
    //   176: new 146	com/android/cglib/dx/b/a/a$6
    //   179: dup
    //   180: ldc 148
    //   182: bipush 13
    //   184: invokespecial 149	com/android/cglib/dx/b/a/a$6:<init>	(Ljava/lang/String;I)V
    //   187: putstatic 151	com/android/cglib/dx/b/a/a:n	Lcom/android/cglib/dx/b/a/a;
    //   190: new 153	com/android/cglib/dx/b/a/a$7
    //   193: dup
    //   194: ldc 155
    //   196: bipush 14
    //   198: invokespecial 156	com/android/cglib/dx/b/a/a$7:<init>	(Ljava/lang/String;I)V
    //   201: putstatic 158	com/android/cglib/dx/b/a/a:o	Lcom/android/cglib/dx/b/a/a;
    //   204: new 160	com/android/cglib/dx/b/a/a$8
    //   207: dup
    //   208: ldc 162
    //   210: bipush 15
    //   212: invokespecial 163	com/android/cglib/dx/b/a/a$8:<init>	(Ljava/lang/String;I)V
    //   215: putstatic 165	com/android/cglib/dx/b/a/a:p	Lcom/android/cglib/dx/b/a/a;
    //   218: new 167	com/android/cglib/dx/b/a/a$9
    //   221: dup
    //   222: ldc 169
    //   224: bipush 16
    //   226: invokespecial 170	com/android/cglib/dx/b/a/a$9:<init>	(Ljava/lang/String;I)V
    //   229: putstatic 172	com/android/cglib/dx/b/a/a:q	Lcom/android/cglib/dx/b/a/a;
    //   232: new 174	com/android/cglib/dx/b/a/a$10
    //   235: dup
    //   236: ldc 176
    //   238: bipush 17
    //   240: invokespecial 177	com/android/cglib/dx/b/a/a$10:<init>	(Ljava/lang/String;I)V
    //   243: putstatic 179	com/android/cglib/dx/b/a/a:r	Lcom/android/cglib/dx/b/a/a;
    //   246: new 181	com/android/cglib/dx/b/a/a$11
    //   249: dup
    //   250: ldc 183
    //   252: bipush 18
    //   254: invokespecial 184	com/android/cglib/dx/b/a/a$11:<init>	(Ljava/lang/String;I)V
    //   257: putstatic 186	com/android/cglib/dx/b/a/a:s	Lcom/android/cglib/dx/b/a/a;
    //   260: new 188	com/android/cglib/dx/b/a/a$13
    //   263: dup
    //   264: ldc 190
    //   266: bipush 19
    //   268: invokespecial 191	com/android/cglib/dx/b/a/a$13:<init>	(Ljava/lang/String;I)V
    //   271: putstatic 193	com/android/cglib/dx/b/a/a:t	Lcom/android/cglib/dx/b/a/a;
    //   274: new 195	com/android/cglib/dx/b/a/a$14
    //   277: dup
    //   278: ldc 197
    //   280: bipush 20
    //   282: invokespecial 198	com/android/cglib/dx/b/a/a$14:<init>	(Ljava/lang/String;I)V
    //   285: putstatic 200	com/android/cglib/dx/b/a/a:u	Lcom/android/cglib/dx/b/a/a;
    //   288: new 202	com/android/cglib/dx/b/a/a$15
    //   291: dup
    //   292: ldc 204
    //   294: bipush 21
    //   296: invokespecial 205	com/android/cglib/dx/b/a/a$15:<init>	(Ljava/lang/String;I)V
    //   299: putstatic 207	com/android/cglib/dx/b/a/a:v	Lcom/android/cglib/dx/b/a/a;
    //   302: new 209	com/android/cglib/dx/b/a/a$16
    //   305: dup
    //   306: ldc 211
    //   308: bipush 22
    //   310: invokespecial 212	com/android/cglib/dx/b/a/a$16:<init>	(Ljava/lang/String;I)V
    //   313: putstatic 214	com/android/cglib/dx/b/a/a:w	Lcom/android/cglib/dx/b/a/a;
    //   316: new 216	com/android/cglib/dx/b/a/a$17
    //   319: dup
    //   320: ldc 218
    //   322: bipush 23
    //   324: invokespecial 219	com/android/cglib/dx/b/a/a$17:<init>	(Ljava/lang/String;I)V
    //   327: putstatic 221	com/android/cglib/dx/b/a/a:x	Lcom/android/cglib/dx/b/a/a;
    //   330: new 223	com/android/cglib/dx/b/a/a$18
    //   333: dup
    //   334: ldc 225
    //   336: bipush 24
    //   338: invokespecial 226	com/android/cglib/dx/b/a/a$18:<init>	(Ljava/lang/String;I)V
    //   341: putstatic 228	com/android/cglib/dx/b/a/a:y	Lcom/android/cglib/dx/b/a/a;
    //   344: new 230	com/android/cglib/dx/b/a/a$19
    //   347: dup
    //   348: ldc 232
    //   350: bipush 25
    //   352: invokespecial 233	com/android/cglib/dx/b/a/a$19:<init>	(Ljava/lang/String;I)V
    //   355: putstatic 235	com/android/cglib/dx/b/a/a:z	Lcom/android/cglib/dx/b/a/a;
    //   358: new 237	com/android/cglib/dx/b/a/a$20
    //   361: dup
    //   362: ldc 239
    //   364: bipush 26
    //   366: invokespecial 240	com/android/cglib/dx/b/a/a$20:<init>	(Ljava/lang/String;I)V
    //   369: putstatic 242	com/android/cglib/dx/b/a/a:A	Lcom/android/cglib/dx/b/a/a;
    //   372: new 244	com/android/cglib/dx/b/a/a$21
    //   375: dup
    //   376: ldc 246
    //   378: bipush 27
    //   380: invokespecial 247	com/android/cglib/dx/b/a/a$21:<init>	(Ljava/lang/String;I)V
    //   383: putstatic 249	com/android/cglib/dx/b/a/a:B	Lcom/android/cglib/dx/b/a/a;
    //   386: new 251	com/android/cglib/dx/b/a/a$22
    //   389: dup
    //   390: ldc 253
    //   392: bipush 28
    //   394: invokespecial 254	com/android/cglib/dx/b/a/a$22:<init>	(Ljava/lang/String;I)V
    //   397: putstatic 256	com/android/cglib/dx/b/a/a:C	Lcom/android/cglib/dx/b/a/a;
    //   400: new 258	com/android/cglib/dx/b/a/a$24
    //   403: dup
    //   404: ldc_w 260
    //   407: bipush 29
    //   409: invokespecial 261	com/android/cglib/dx/b/a/a$24:<init>	(Ljava/lang/String;I)V
    //   412: putstatic 263	com/android/cglib/dx/b/a/a:D	Lcom/android/cglib/dx/b/a/a;
    //   415: new 265	com/android/cglib/dx/b/a/a$25
    //   418: dup
    //   419: ldc_w 267
    //   422: bipush 30
    //   424: invokespecial 268	com/android/cglib/dx/b/a/a$25:<init>	(Ljava/lang/String;I)V
    //   427: putstatic 270	com/android/cglib/dx/b/a/a:E	Lcom/android/cglib/dx/b/a/a;
    //   430: new 272	com/android/cglib/dx/b/a/a$26
    //   433: dup
    //   434: ldc_w 274
    //   437: bipush 31
    //   439: invokespecial 275	com/android/cglib/dx/b/a/a$26:<init>	(Ljava/lang/String;I)V
    //   442: putstatic 277	com/android/cglib/dx/b/a/a:F	Lcom/android/cglib/dx/b/a/a;
    //   445: new 279	com/android/cglib/dx/b/a/a$27
    //   448: dup
    //   449: ldc_w 281
    //   452: bipush 32
    //   454: invokespecial 282	com/android/cglib/dx/b/a/a$27:<init>	(Ljava/lang/String;I)V
    //   457: putstatic 284	com/android/cglib/dx/b/a/a:G	Lcom/android/cglib/dx/b/a/a;
    //   460: new 286	com/android/cglib/dx/b/a/a$28
    //   463: dup
    //   464: ldc_w 288
    //   467: bipush 33
    //   469: invokespecial 289	com/android/cglib/dx/b/a/a$28:<init>	(Ljava/lang/String;I)V
    //   472: putstatic 291	com/android/cglib/dx/b/a/a:H	Lcom/android/cglib/dx/b/a/a;
    //   475: new 293	com/android/cglib/dx/b/a/a$29
    //   478: dup
    //   479: ldc_w 295
    //   482: bipush 34
    //   484: invokespecial 296	com/android/cglib/dx/b/a/a$29:<init>	(Ljava/lang/String;I)V
    //   487: putstatic 298	com/android/cglib/dx/b/a/a:I	Lcom/android/cglib/dx/b/a/a;
    //   490: new 300	com/android/cglib/dx/b/a/a$30
    //   493: dup
    //   494: ldc_w 302
    //   497: bipush 35
    //   499: invokespecial 303	com/android/cglib/dx/b/a/a$30:<init>	(Ljava/lang/String;I)V
    //   502: putstatic 305	com/android/cglib/dx/b/a/a:J	Lcom/android/cglib/dx/b/a/a;
    //   505: new 307	com/android/cglib/dx/b/a/a$31
    //   508: dup
    //   509: ldc_w 309
    //   512: bipush 36
    //   514: invokespecial 310	com/android/cglib/dx/b/a/a$31:<init>	(Ljava/lang/String;I)V
    //   517: putstatic 312	com/android/cglib/dx/b/a/a:K	Lcom/android/cglib/dx/b/a/a;
    //   520: new 314	com/android/cglib/dx/b/a/a$32
    //   523: dup
    //   524: ldc_w 316
    //   527: bipush 37
    //   529: invokespecial 317	com/android/cglib/dx/b/a/a$32:<init>	(Ljava/lang/String;I)V
    //   532: putstatic 319	com/android/cglib/dx/b/a/a:L	Lcom/android/cglib/dx/b/a/a;
    //   535: new 321	com/android/cglib/dx/b/a/a$33
    //   538: dup
    //   539: ldc_w 323
    //   542: bipush 38
    //   544: invokespecial 324	com/android/cglib/dx/b/a/a$33:<init>	(Ljava/lang/String;I)V
    //   547: putstatic 326	com/android/cglib/dx/b/a/a:M	Lcom/android/cglib/dx/b/a/a;
    //   550: new 328	com/android/cglib/dx/b/a/a$35
    //   553: dup
    //   554: ldc_w 330
    //   557: bipush 39
    //   559: invokespecial 331	com/android/cglib/dx/b/a/a$35:<init>	(Ljava/lang/String;I)V
    //   562: putstatic 333	com/android/cglib/dx/b/a/a:N	Lcom/android/cglib/dx/b/a/a;
    //   565: bipush 40
    //   567: anewarray 2	com/android/cglib/dx/b/a/a
    //   570: astore_0
    //   571: aload_0
    //   572: iconst_0
    //   573: getstatic 60	com/android/cglib/dx/b/a/a:a	Lcom/android/cglib/dx/b/a/a;
    //   576: aastore
    //   577: aload_0
    //   578: iconst_1
    //   579: getstatic 67	com/android/cglib/dx/b/a/a:b	Lcom/android/cglib/dx/b/a/a;
    //   582: aastore
    //   583: aload_0
    //   584: iconst_2
    //   585: getstatic 74	com/android/cglib/dx/b/a/a:c	Lcom/android/cglib/dx/b/a/a;
    //   588: aastore
    //   589: aload_0
    //   590: iconst_3
    //   591: getstatic 81	com/android/cglib/dx/b/a/a:d	Lcom/android/cglib/dx/b/a/a;
    //   594: aastore
    //   595: aload_0
    //   596: iconst_4
    //   597: getstatic 88	com/android/cglib/dx/b/a/a:e	Lcom/android/cglib/dx/b/a/a;
    //   600: aastore
    //   601: aload_0
    //   602: iconst_5
    //   603: getstatic 95	com/android/cglib/dx/b/a/a:f	Lcom/android/cglib/dx/b/a/a;
    //   606: aastore
    //   607: aload_0
    //   608: bipush 6
    //   610: getstatic 102	com/android/cglib/dx/b/a/a:g	Lcom/android/cglib/dx/b/a/a;
    //   613: aastore
    //   614: aload_0
    //   615: bipush 7
    //   617: getstatic 109	com/android/cglib/dx/b/a/a:h	Lcom/android/cglib/dx/b/a/a;
    //   620: aastore
    //   621: aload_0
    //   622: bipush 8
    //   624: getstatic 116	com/android/cglib/dx/b/a/a:i	Lcom/android/cglib/dx/b/a/a;
    //   627: aastore
    //   628: aload_0
    //   629: bipush 9
    //   631: getstatic 123	com/android/cglib/dx/b/a/a:j	Lcom/android/cglib/dx/b/a/a;
    //   634: aastore
    //   635: aload_0
    //   636: bipush 10
    //   638: getstatic 130	com/android/cglib/dx/b/a/a:k	Lcom/android/cglib/dx/b/a/a;
    //   641: aastore
    //   642: aload_0
    //   643: bipush 11
    //   645: getstatic 137	com/android/cglib/dx/b/a/a:l	Lcom/android/cglib/dx/b/a/a;
    //   648: aastore
    //   649: aload_0
    //   650: bipush 12
    //   652: getstatic 144	com/android/cglib/dx/b/a/a:m	Lcom/android/cglib/dx/b/a/a;
    //   655: aastore
    //   656: aload_0
    //   657: bipush 13
    //   659: getstatic 151	com/android/cglib/dx/b/a/a:n	Lcom/android/cglib/dx/b/a/a;
    //   662: aastore
    //   663: aload_0
    //   664: bipush 14
    //   666: getstatic 158	com/android/cglib/dx/b/a/a:o	Lcom/android/cglib/dx/b/a/a;
    //   669: aastore
    //   670: aload_0
    //   671: bipush 15
    //   673: getstatic 165	com/android/cglib/dx/b/a/a:p	Lcom/android/cglib/dx/b/a/a;
    //   676: aastore
    //   677: aload_0
    //   678: bipush 16
    //   680: getstatic 172	com/android/cglib/dx/b/a/a:q	Lcom/android/cglib/dx/b/a/a;
    //   683: aastore
    //   684: aload_0
    //   685: bipush 17
    //   687: getstatic 179	com/android/cglib/dx/b/a/a:r	Lcom/android/cglib/dx/b/a/a;
    //   690: aastore
    //   691: aload_0
    //   692: bipush 18
    //   694: getstatic 186	com/android/cglib/dx/b/a/a:s	Lcom/android/cglib/dx/b/a/a;
    //   697: aastore
    //   698: aload_0
    //   699: bipush 19
    //   701: getstatic 193	com/android/cglib/dx/b/a/a:t	Lcom/android/cglib/dx/b/a/a;
    //   704: aastore
    //   705: aload_0
    //   706: bipush 20
    //   708: getstatic 200	com/android/cglib/dx/b/a/a:u	Lcom/android/cglib/dx/b/a/a;
    //   711: aastore
    //   712: aload_0
    //   713: bipush 21
    //   715: getstatic 207	com/android/cglib/dx/b/a/a:v	Lcom/android/cglib/dx/b/a/a;
    //   718: aastore
    //   719: aload_0
    //   720: bipush 22
    //   722: getstatic 214	com/android/cglib/dx/b/a/a:w	Lcom/android/cglib/dx/b/a/a;
    //   725: aastore
    //   726: aload_0
    //   727: bipush 23
    //   729: getstatic 221	com/android/cglib/dx/b/a/a:x	Lcom/android/cglib/dx/b/a/a;
    //   732: aastore
    //   733: aload_0
    //   734: bipush 24
    //   736: getstatic 228	com/android/cglib/dx/b/a/a:y	Lcom/android/cglib/dx/b/a/a;
    //   739: aastore
    //   740: aload_0
    //   741: bipush 25
    //   743: getstatic 235	com/android/cglib/dx/b/a/a:z	Lcom/android/cglib/dx/b/a/a;
    //   746: aastore
    //   747: aload_0
    //   748: bipush 26
    //   750: getstatic 242	com/android/cglib/dx/b/a/a:A	Lcom/android/cglib/dx/b/a/a;
    //   753: aastore
    //   754: aload_0
    //   755: bipush 27
    //   757: getstatic 249	com/android/cglib/dx/b/a/a:B	Lcom/android/cglib/dx/b/a/a;
    //   760: aastore
    //   761: aload_0
    //   762: bipush 28
    //   764: getstatic 256	com/android/cglib/dx/b/a/a:C	Lcom/android/cglib/dx/b/a/a;
    //   767: aastore
    //   768: aload_0
    //   769: bipush 29
    //   771: getstatic 263	com/android/cglib/dx/b/a/a:D	Lcom/android/cglib/dx/b/a/a;
    //   774: aastore
    //   775: aload_0
    //   776: bipush 30
    //   778: getstatic 270	com/android/cglib/dx/b/a/a:E	Lcom/android/cglib/dx/b/a/a;
    //   781: aastore
    //   782: aload_0
    //   783: bipush 31
    //   785: getstatic 277	com/android/cglib/dx/b/a/a:F	Lcom/android/cglib/dx/b/a/a;
    //   788: aastore
    //   789: aload_0
    //   790: bipush 32
    //   792: getstatic 284	com/android/cglib/dx/b/a/a:G	Lcom/android/cglib/dx/b/a/a;
    //   795: aastore
    //   796: aload_0
    //   797: bipush 33
    //   799: getstatic 291	com/android/cglib/dx/b/a/a:H	Lcom/android/cglib/dx/b/a/a;
    //   802: aastore
    //   803: aload_0
    //   804: bipush 34
    //   806: getstatic 298	com/android/cglib/dx/b/a/a:I	Lcom/android/cglib/dx/b/a/a;
    //   809: aastore
    //   810: aload_0
    //   811: bipush 35
    //   813: getstatic 305	com/android/cglib/dx/b/a/a:J	Lcom/android/cglib/dx/b/a/a;
    //   816: aastore
    //   817: aload_0
    //   818: bipush 36
    //   820: getstatic 312	com/android/cglib/dx/b/a/a:K	Lcom/android/cglib/dx/b/a/a;
    //   823: aastore
    //   824: aload_0
    //   825: bipush 37
    //   827: getstatic 319	com/android/cglib/dx/b/a/a:L	Lcom/android/cglib/dx/b/a/a;
    //   830: aastore
    //   831: aload_0
    //   832: bipush 38
    //   834: getstatic 326	com/android/cglib/dx/b/a/a:M	Lcom/android/cglib/dx/b/a/a;
    //   837: aastore
    //   838: aload_0
    //   839: bipush 39
    //   841: getstatic 333	com/android/cglib/dx/b/a/a:N	Lcom/android/cglib/dx/b/a/a;
    //   844: aastore
    //   845: aload_0
    //   846: putstatic 335	com/android/cglib/dx/b/a/a:O	[Lcom/android/cglib/dx/b/a/a;
    //   849: return
  }
}

/* Location:           C:\Users\86186\Downloads\反编译工具包\01_反编译工具包\dex2jar-0.0.9.15\dex2jar-0.0.9.15\classes_dex2jar.jar
 * Qualified Name:     com.android.cglib.dx.b.a.a
 * JD-Core Version:    0.6.2
 */