package com.baidu.mobstat;

import android.content.Context;
import android.content.res.Configuration;
import android.content.res.Resources;
import android.telephony.TelephonyManager;
import org.json.JSONObject;

class bu
{
  static String a = "Android";
  boolean b = false;
  String c;
  String d;
  String e = "0";
  String f = null;
  String g = null;
  int h = -1;
  String i;
  String j;
  int k;
  int l;
  String m = null;
  String n;
  String o;
  String p;
  String q;
  String r;
  String s;
  String t;
  String u;
  String v;
  String w;
  String x;
  JSONObject y;
  int z = 0;

  public void a(Context paramContext)
  {
    while (true)
    {
      try
      {
        boolean bool1 = this.b;
        if (bool1)
          return;
        cs.e(paramContext, "android.permission.READ_PHONE_STATE");
        cs.e(paramContext, "android.permission.INTERNET");
        cs.e(paramContext, "android.permission.ACCESS_NETWORK_STATE");
        cs.e(paramContext, "android.permission.WRITE_SETTINGS");
        TelephonyManager localTelephonyManager = (TelephonyManager)paramContext.getSystemService("phone");
        this.c = CooperService.a().getOSVersion();
        this.d = CooperService.a().getOSSysVersion();
        this.o = CooperService.a().getPhoneModel();
        this.p = CooperService.a().getManufacturer();
        this.x = CooperService.a().getUUID();
        this.y = CooperService.a().getHeaderExt(paramContext);
        this.j = CooperService.a().getDeviceId(localTelephonyManager, paramContext);
        if (bj.a().i(paramContext))
        {
          str1 = "1";
          this.e = str1;
          if (dc.s(paramContext))
            this.e = "2";
          StringBuilder localStringBuilder = new StringBuilder();
          localStringBuilder.append(this.e);
          localStringBuilder.append("-0");
          this.e = localStringBuilder.toString();
          try
          {
            boolean bool2 = CooperService.a().isDeviceMacEnabled(paramContext);
            this.t = CooperService.a().getMacAddress(paramContext, bool2);
          }
          catch (Exception localException1)
          {
            cz.a(localException1);
          }
          try
          {
            this.v = dc.f(1, paramContext);
          }
          catch (Exception localException2)
          {
            cz.a(localException2);
          }
          try
          {
            this.w = dc.a(paramContext, 1);
          }
          catch (Exception localException3)
          {
            cz.a(localException3);
          }
          this.g = CooperService.a().getCUID(paramContext, true);
          try
          {
            this.n = CooperService.a().getOperator(localTelephonyManager);
          }
          catch (Exception localException4)
          {
            cz.a(localException4);
          }
          try
          {
            this.k = dc.b(paramContext);
            this.l = dc.c(paramContext);
            if (paramContext.getResources().getConfiguration().orientation == 2)
            {
              this.k ^= this.l;
              this.l = (this.k ^ this.l);
              this.k ^= this.l;
            }
          }
          catch (Exception localException5)
          {
            cz.a(localException5);
          }
          this.m = CooperService.a().getAppChannel(paramContext);
          this.f = CooperService.a().getAppKey(paramContext);
          try
          {
            this.h = CooperService.a().getAppVersionCode(paramContext);
            this.i = CooperService.a().getAppVersionName(paramContext);
          }
          catch (Exception localException6)
          {
            cz.a(localException6);
          }
          try
          {
            String str3;
            if (CooperService.a().checkCellLocationSetting(paramContext))
            {
              str3 = dc.g(paramContext);
              this.q = str3;
            }
            else
            {
              str3 = "0_0_0";
              continue;
            }
          }
          catch (Exception localException7)
          {
            cz.a(localException7);
            try
            {
              String str2;
              if (CooperService.a().checkGPSLocationSetting(paramContext))
              {
                str2 = dc.h(paramContext);
                this.r = str2;
              }
              else
              {
                str2 = "";
                continue;
              }
            }
            catch (Exception localException8)
            {
              cz.a(localException8);
              try
              {
                this.s = CooperService.a().getLinkedWay(paramContext);
              }
              catch (Exception localException9)
              {
                cz.a(localException9);
              }
              this.b = true;
              return;
            }
          }
        }
      }
      finally
      {
      }
      String str1 = "0";
    }
  }

  public void a(Context paramContext, JSONObject paramJSONObject)
  {
    try
    {
      a(paramContext);
      if (paramJSONObject.length() > 10)
      {
        StringBuilder localStringBuilder = new StringBuilder();
        localStringBuilder.append("header has been installed; header is:");
        localStringBuilder.append(paramJSONObject);
        cz.a(localStringBuilder.toString());
        return;
      }
      b(paramContext, paramJSONObject);
      return;
    }
    finally
    {
    }
  }

  public void a(JSONObject paramJSONObject)
  {
    this.y = paramJSONObject;
  }

  // ERROR //
  public void b(Context paramContext, JSONObject paramJSONObject)
  {
    // Byte code:
    //   0: aload_0
    //   1: monitorenter
    //   2: getstatic 273	com/baidu/mobstat/bu:a	Ljava/lang/String;
    //   5: ifnonnull +10 -> 15
    //   8: ldc 244
    //   10: astore 4
    //   12: goto +8 -> 20
    //   15: getstatic 273	com/baidu/mobstat/bu:a	Ljava/lang/String;
    //   18: astore 4
    //   20: aload_2
    //   21: ldc_w 274
    //   24: aload 4
    //   26: invokevirtual 278	org/json/JSONObject:put	(Ljava/lang/String;Ljava/lang/Object;)Lorg/json/JSONObject;
    //   29: pop
    //   30: aload_2
    //   31: ldc_w 280
    //   34: iconst_0
    //   35: invokevirtual 283	org/json/JSONObject:put	(Ljava/lang/String;I)Lorg/json/JSONObject;
    //   38: pop
    //   39: aload_0
    //   40: getfield 94	com/baidu/mobstat/bu:c	Ljava/lang/String;
    //   43: ifnonnull +10 -> 53
    //   46: ldc 244
    //   48: astore 7
    //   50: goto +9 -> 59
    //   53: aload_0
    //   54: getfield 94	com/baidu/mobstat/bu:c	Ljava/lang/String;
    //   57: astore 7
    //   59: aload_2
    //   60: ldc_w 284
    //   63: aload 7
    //   65: invokevirtual 278	org/json/JSONObject:put	(Ljava/lang/String;Ljava/lang/Object;)Lorg/json/JSONObject;
    //   68: pop
    //   69: aload_0
    //   70: getfield 99	com/baidu/mobstat/bu:d	Ljava/lang/String;
    //   73: ifnonnull +10 -> 83
    //   76: ldc 244
    //   78: astore 9
    //   80: goto +9 -> 89
    //   83: aload_0
    //   84: getfield 99	com/baidu/mobstat/bu:d	Ljava/lang/String;
    //   87: astore 9
    //   89: aload_2
    //   90: ldc_w 286
    //   93: aload 9
    //   95: invokevirtual 278	org/json/JSONObject:put	(Ljava/lang/String;Ljava/lang/Object;)Lorg/json/JSONObject;
    //   98: pop
    //   99: aload_0
    //   100: getfield 49	com/baidu/mobstat/bu:f	Ljava/lang/String;
    //   103: ifnonnull +10 -> 113
    //   106: ldc 244
    //   108: astore 11
    //   110: goto +9 -> 119
    //   113: aload_0
    //   114: getfield 49	com/baidu/mobstat/bu:f	Ljava/lang/String;
    //   117: astore 11
    //   119: aload_2
    //   120: ldc_w 287
    //   123: aload 11
    //   125: invokevirtual 278	org/json/JSONObject:put	(Ljava/lang/String;Ljava/lang/Object;)Lorg/json/JSONObject;
    //   128: pop
    //   129: aload_0
    //   130: getfield 47	com/baidu/mobstat/bu:e	Ljava/lang/String;
    //   133: ifnonnull +10 -> 143
    //   136: ldc 45
    //   138: astore 13
    //   140: goto +9 -> 149
    //   143: aload_0
    //   144: getfield 47	com/baidu/mobstat/bu:e	Ljava/lang/String;
    //   147: astore 13
    //   149: aload_2
    //   150: ldc_w 289
    //   153: aload 13
    //   155: invokevirtual 278	org/json/JSONObject:put	(Ljava/lang/String;Ljava/lang/Object;)Lorg/json/JSONObject;
    //   158: pop
    //   159: aload_2
    //   160: ldc_w 290
    //   163: ldc 244
    //   165: invokevirtual 278	org/json/JSONObject:put	(Ljava/lang/String;Ljava/lang/Object;)Lorg/json/JSONObject;
    //   168: pop
    //   169: aload_2
    //   170: ldc_w 291
    //   173: ldc_w 293
    //   176: invokevirtual 278	org/json/JSONObject:put	(Ljava/lang/String;Ljava/lang/Object;)Lorg/json/JSONObject;
    //   179: pop
    //   180: aload_2
    //   181: ldc_w 295
    //   184: iconst_0
    //   185: invokevirtual 283	org/json/JSONObject:put	(Ljava/lang/String;I)Lorg/json/JSONObject;
    //   188: pop
    //   189: aload_2
    //   190: ldc_w 296
    //   193: aload_0
    //   194: getfield 53	com/baidu/mobstat/bu:h	I
    //   197: invokevirtual 283	org/json/JSONObject:put	(Ljava/lang/String;I)Lorg/json/JSONObject;
    //   200: pop
    //   201: aload_0
    //   202: getfield 226	com/baidu/mobstat/bu:i	Ljava/lang/String;
    //   205: ifnonnull +10 -> 215
    //   208: ldc 244
    //   210: astore 19
    //   212: goto +9 -> 221
    //   215: aload_0
    //   216: getfield 226	com/baidu/mobstat/bu:i	Ljava/lang/String;
    //   219: astore 19
    //   221: aload_2
    //   222: ldc_w 297
    //   225: aload 19
    //   227: invokevirtual 278	org/json/JSONObject:put	(Ljava/lang/String;Ljava/lang/Object;)Lorg/json/JSONObject;
    //   230: pop
    //   231: aload_2
    //   232: ldc_w 298
    //   235: ldc 244
    //   237: invokevirtual 278	org/json/JSONObject:put	(Ljava/lang/String;Ljava/lang/Object;)Lorg/json/JSONObject;
    //   240: pop
    //   241: aload_0
    //   242: getfield 163	com/baidu/mobstat/bu:t	Ljava/lang/String;
    //   245: ifnonnull +10 -> 255
    //   248: ldc 244
    //   250: astore 22
    //   252: goto +9 -> 261
    //   255: aload_0
    //   256: getfield 163	com/baidu/mobstat/bu:t	Ljava/lang/String;
    //   259: astore 22
    //   261: aload_2
    //   262: ldc_w 300
    //   265: aload 22
    //   267: invokevirtual 278	org/json/JSONObject:put	(Ljava/lang/String;Ljava/lang/Object;)Lorg/json/JSONObject;
    //   270: pop
    //   271: aload_0
    //   272: getfield 173	com/baidu/mobstat/bu:v	Ljava/lang/String;
    //   275: ifnonnull +10 -> 285
    //   278: ldc 244
    //   280: astore 24
    //   282: goto +9 -> 291
    //   285: aload_0
    //   286: getfield 173	com/baidu/mobstat/bu:v	Ljava/lang/String;
    //   289: astore 24
    //   291: aload_2
    //   292: ldc_w 302
    //   295: aload 24
    //   297: invokevirtual 278	org/json/JSONObject:put	(Ljava/lang/String;Ljava/lang/Object;)Lorg/json/JSONObject;
    //   300: pop
    //   301: aload_0
    //   302: getfield 126	com/baidu/mobstat/bu:j	Ljava/lang/String;
    //   305: ifnonnull +10 -> 315
    //   308: ldc 244
    //   310: astore 26
    //   312: goto +9 -> 321
    //   315: aload_0
    //   316: getfield 126	com/baidu/mobstat/bu:j	Ljava/lang/String;
    //   319: astore 26
    //   321: aload_2
    //   322: ldc_w 304
    //   325: aload 26
    //   327: invokevirtual 278	org/json/JSONObject:put	(Ljava/lang/String;Ljava/lang/Object;)Lorg/json/JSONObject;
    //   330: pop
    //   331: aload_0
    //   332: getfield 51	com/baidu/mobstat/bu:g	Ljava/lang/String;
    //   335: ifnonnull +10 -> 345
    //   338: ldc 244
    //   340: astore 28
    //   342: goto +9 -> 351
    //   345: aload_0
    //   346: getfield 51	com/baidu/mobstat/bu:g	Ljava/lang/String;
    //   349: astore 28
    //   351: aload_2
    //   352: ldc_w 306
    //   355: aload 28
    //   357: invokevirtual 278	org/json/JSONObject:put	(Ljava/lang/String;Ljava/lang/Object;)Lorg/json/JSONObject;
    //   360: pop
    //   361: aload_2
    //   362: ldc_w 308
    //   365: iconst_1
    //   366: invokevirtual 283	org/json/JSONObject:put	(Ljava/lang/String;I)Lorg/json/JSONObject;
    //   369: pop
    //   370: aload_2
    //   371: ldc_w 309
    //   374: aload_0
    //   375: getfield 192	com/baidu/mobstat/bu:k	I
    //   378: invokevirtual 283	org/json/JSONObject:put	(Ljava/lang/String;I)Lorg/json/JSONObject;
    //   381: pop
    //   382: aload_2
    //   383: ldc_w 310
    //   386: aload_0
    //   387: getfield 196	com/baidu/mobstat/bu:l	I
    //   390: invokevirtual 283	org/json/JSONObject:put	(Ljava/lang/String;I)Lorg/json/JSONObject;
    //   393: pop
    //   394: aload_0
    //   395: getfield 178	com/baidu/mobstat/bu:w	Ljava/lang/String;
    //   398: ifnonnull +10 -> 408
    //   401: ldc 244
    //   403: astore 33
    //   405: goto +9 -> 414
    //   408: aload_0
    //   409: getfield 178	com/baidu/mobstat/bu:w	Ljava/lang/String;
    //   412: astore 33
    //   414: aload_2
    //   415: ldc_w 312
    //   418: aload 33
    //   420: invokevirtual 278	org/json/JSONObject:put	(Ljava/lang/String;Ljava/lang/Object;)Lorg/json/JSONObject;
    //   423: pop
    //   424: aload_0
    //   425: getfield 55	com/baidu/mobstat/bu:m	Ljava/lang/String;
    //   428: ifnonnull +10 -> 438
    //   431: ldc 244
    //   433: astore 35
    //   435: goto +9 -> 444
    //   438: aload_0
    //   439: getfield 55	com/baidu/mobstat/bu:m	Ljava/lang/String;
    //   442: astore 35
    //   444: aload_2
    //   445: ldc_w 313
    //   448: aload 35
    //   450: invokevirtual 278	org/json/JSONObject:put	(Ljava/lang/String;Ljava/lang/Object;)Lorg/json/JSONObject;
    //   453: pop
    //   454: aload_0
    //   455: getfield 187	com/baidu/mobstat/bu:n	Ljava/lang/String;
    //   458: ifnonnull +10 -> 468
    //   461: ldc 244
    //   463: astore 37
    //   465: goto +9 -> 474
    //   468: aload_0
    //   469: getfield 187	com/baidu/mobstat/bu:n	Ljava/lang/String;
    //   472: astore 37
    //   474: aload_2
    //   475: ldc_w 315
    //   478: aload 37
    //   480: invokevirtual 278	org/json/JSONObject:put	(Ljava/lang/String;Ljava/lang/Object;)Lorg/json/JSONObject;
    //   483: pop
    //   484: aload_0
    //   485: getfield 104	com/baidu/mobstat/bu:o	Ljava/lang/String;
    //   488: ifnonnull +10 -> 498
    //   491: ldc 244
    //   493: astore 39
    //   495: goto +9 -> 504
    //   498: aload_0
    //   499: getfield 104	com/baidu/mobstat/bu:o	Ljava/lang/String;
    //   502: astore 39
    //   504: aload_2
    //   505: ldc_w 316
    //   508: aload 39
    //   510: invokevirtual 278	org/json/JSONObject:put	(Ljava/lang/String;Ljava/lang/Object;)Lorg/json/JSONObject;
    //   513: pop
    //   514: aload_0
    //   515: getfield 109	com/baidu/mobstat/bu:p	Ljava/lang/String;
    //   518: ifnonnull +10 -> 528
    //   521: ldc 244
    //   523: astore 41
    //   525: goto +9 -> 534
    //   528: aload_0
    //   529: getfield 109	com/baidu/mobstat/bu:p	Ljava/lang/String;
    //   532: astore 41
    //   534: aload_2
    //   535: ldc_w 318
    //   538: aload 41
    //   540: invokevirtual 278	org/json/JSONObject:put	(Ljava/lang/String;Ljava/lang/Object;)Lorg/json/JSONObject;
    //   543: pop
    //   544: aload_2
    //   545: ldc_w 320
    //   548: aload_0
    //   549: getfield 233	com/baidu/mobstat/bu:q	Ljava/lang/String;
    //   552: invokevirtual 278	org/json/JSONObject:put	(Ljava/lang/String;Ljava/lang/Object;)Lorg/json/JSONObject;
    //   555: pop
    //   556: aload_0
    //   557: getfield 242	com/baidu/mobstat/bu:r	Ljava/lang/String;
    //   560: ifnonnull +10 -> 570
    //   563: ldc 244
    //   565: astore 44
    //   567: goto +9 -> 576
    //   570: aload_0
    //   571: getfield 242	com/baidu/mobstat/bu:r	Ljava/lang/String;
    //   574: astore 44
    //   576: aload_2
    //   577: ldc_w 322
    //   580: aload 44
    //   582: invokevirtual 278	org/json/JSONObject:put	(Ljava/lang/String;Ljava/lang/Object;)Lorg/json/JSONObject;
    //   585: pop
    //   586: aload_0
    //   587: getfield 249	com/baidu/mobstat/bu:s	Ljava/lang/String;
    //   590: ifnonnull +10 -> 600
    //   593: ldc 244
    //   595: astore 46
    //   597: goto +9 -> 606
    //   600: aload_0
    //   601: getfield 249	com/baidu/mobstat/bu:s	Ljava/lang/String;
    //   604: astore 46
    //   606: aload_2
    //   607: ldc_w 323
    //   610: aload 46
    //   612: invokevirtual 278	org/json/JSONObject:put	(Ljava/lang/String;Ljava/lang/Object;)Lorg/json/JSONObject;
    //   615: pop
    //   616: aload_2
    //   617: ldc_w 324
    //   620: invokestatic 330	java/lang/System:currentTimeMillis	()J
    //   623: invokevirtual 333	org/json/JSONObject:put	(Ljava/lang/String;J)Lorg/json/JSONObject;
    //   626: pop
    //   627: aload_2
    //   628: ldc_w 335
    //   631: aload_0
    //   632: getfield 57	com/baidu/mobstat/bu:z	I
    //   635: invokevirtual 283	org/json/JSONObject:put	(Ljava/lang/String;I)Lorg/json/JSONObject;
    //   638: pop
    //   639: aload_2
    //   640: ldc_w 337
    //   643: iconst_1
    //   644: aload_1
    //   645: invokestatic 339	com/baidu/mobstat/dc:h	(ILandroid/content/Context;)Ljava/lang/String;
    //   648: invokevirtual 278	org/json/JSONObject:put	(Ljava/lang/String;Ljava/lang/Object;)Lorg/json/JSONObject;
    //   651: pop
    //   652: aload_1
    //   653: invokestatic 341	com/baidu/mobstat/dc:q	(Landroid/content/Context;)Ljava/lang/String;
    //   656: astore 51
    //   658: aload_2
    //   659: ldc_w 343
    //   662: aload 51
    //   664: invokevirtual 278	org/json/JSONObject:put	(Ljava/lang/String;Ljava/lang/Object;)Lorg/json/JSONObject;
    //   667: pop
    //   668: aload 51
    //   670: invokestatic 349	android/text/TextUtils:isEmpty	(Ljava/lang/CharSequence;)Z
    //   673: istore 53
    //   675: aconst_null
    //   676: astore 54
    //   678: iload 53
    //   680: ifne +156 -> 836
    //   683: aload_1
    //   684: invokestatic 351	com/baidu/mobstat/dc:r	(Landroid/content/Context;)Ljava/lang/String;
    //   687: astore 54
    //   689: goto +147 -> 836
    //   692: aload_2
    //   693: ldc_w 353
    //   696: aload 54
    //   698: invokevirtual 278	org/json/JSONObject:put	(Ljava/lang/String;Ljava/lang/Object;)Lorg/json/JSONObject;
    //   701: pop
    //   702: aload_0
    //   703: getfield 114	com/baidu/mobstat/bu:x	Ljava/lang/String;
    //   706: ifnonnull +10 -> 716
    //   709: ldc 244
    //   711: astore 56
    //   713: goto +9 -> 722
    //   716: aload_0
    //   717: getfield 114	com/baidu/mobstat/bu:x	Ljava/lang/String;
    //   720: astore 56
    //   722: aload_2
    //   723: ldc_w 355
    //   726: aload 56
    //   728: invokevirtual 278	org/json/JSONObject:put	(Ljava/lang/String;Ljava/lang/Object;)Lorg/json/JSONObject;
    //   731: pop
    //   732: aload_0
    //   733: getfield 120	com/baidu/mobstat/bu:y	Lorg/json/JSONObject;
    //   736: ifnull +25 -> 761
    //   739: aload_0
    //   740: getfield 120	com/baidu/mobstat/bu:y	Lorg/json/JSONObject;
    //   743: invokevirtual 258	org/json/JSONObject:length	()I
    //   746: ifeq +15 -> 761
    //   749: aload_2
    //   750: ldc_w 357
    //   753: aload_0
    //   754: getfield 120	com/baidu/mobstat/bu:y	Lorg/json/JSONObject;
    //   757: invokevirtual 278	org/json/JSONObject:put	(Ljava/lang/String;Ljava/lang/Object;)Lorg/json/JSONObject;
    //   760: pop
    //   761: new 144	java/lang/StringBuilder
    //   764: dup
    //   765: invokespecial 145	java/lang/StringBuilder:<init>	()V
    //   768: astore 58
    //   770: aload 58
    //   772: ldc_w 359
    //   775: invokevirtual 149	java/lang/StringBuilder:append	(Ljava/lang/String;)Ljava/lang/StringBuilder;
    //   778: pop
    //   779: aload 58
    //   781: aload_2
    //   782: invokevirtual 360	org/json/JSONObject:toString	()Ljava/lang/String;
    //   785: invokevirtual 149	java/lang/StringBuilder:append	(Ljava/lang/String;)Ljava/lang/StringBuilder;
    //   788: pop
    //   789: aload 58
    //   791: ldc_w 362
    //   794: invokevirtual 149	java/lang/StringBuilder:append	(Ljava/lang/String;)Ljava/lang/StringBuilder;
    //   797: pop
    //   798: aload 58
    //   800: aload_2
    //   801: invokevirtual 258	org/json/JSONObject:length	()I
    //   804: invokevirtual 365	java/lang/StringBuilder:append	(I)Ljava/lang/StringBuilder;
    //   807: pop
    //   808: aload 58
    //   810: invokevirtual 154	java/lang/StringBuilder:toString	()Ljava/lang/String;
    //   813: invokestatic 266	com/baidu/mobstat/cz:a	(Ljava/lang/String;)V
    //   816: goto +13 -> 829
    //   819: astore_3
    //   820: goto +12 -> 832
    //   823: ldc_w 367
    //   826: invokestatic 266	com/baidu/mobstat/cz:a	(Ljava/lang/String;)V
    //   829: aload_0
    //   830: monitorexit
    //   831: return
    //   832: aload_0
    //   833: monitorexit
    //   834: aload_3
    //   835: athrow
    //   836: aload 54
    //   838: ifnonnull -146 -> 692
    //   841: ldc 244
    //   843: astore 54
    //   845: goto -153 -> 692
    //
    // Exception table:
    //   from	to	target	type
    //   2	8	819	finally
    //   15	20	819	finally
    //   20	46	819	finally
    //   53	59	819	finally
    //   59	76	819	finally
    //   83	89	819	finally
    //   89	106	819	finally
    //   113	119	819	finally
    //   119	136	819	finally
    //   143	149	819	finally
    //   149	208	819	finally
    //   215	221	819	finally
    //   221	248	819	finally
    //   255	261	819	finally
    //   261	278	819	finally
    //   285	291	819	finally
    //   291	308	819	finally
    //   315	321	819	finally
    //   321	338	819	finally
    //   345	351	819	finally
    //   351	401	819	finally
    //   408	414	819	finally
    //   414	431	819	finally
    //   438	444	819	finally
    //   444	461	819	finally
    //   468	474	819	finally
    //   474	491	819	finally
    //   498	504	819	finally
    //   504	521	819	finally
    //   528	534	819	finally
    //   534	563	819	finally
    //   570	576	819	finally
    //   576	593	819	finally
    //   600	606	819	finally
    //   606	675	819	finally
    //   683	689	819	finally
    //   692	709	819	finally
    //   716	722	819	finally
    //   722	761	819	finally
    //   761	816	819	finally
    //   823	829	819	finally
    //   2	8	823	org/json/JSONException
    //   15	20	823	org/json/JSONException
    //   20	46	823	org/json/JSONException
    //   53	59	823	org/json/JSONException
    //   59	76	823	org/json/JSONException
    //   83	89	823	org/json/JSONException
    //   89	106	823	org/json/JSONException
    //   113	119	823	org/json/JSONException
    //   119	136	823	org/json/JSONException
    //   143	149	823	org/json/JSONException
    //   149	208	823	org/json/JSONException
    //   215	221	823	org/json/JSONException
    //   221	248	823	org/json/JSONException
    //   255	261	823	org/json/JSONException
    //   261	278	823	org/json/JSONException
    //   285	291	823	org/json/JSONException
    //   291	308	823	org/json/JSONException
    //   315	321	823	org/json/JSONException
    //   321	338	823	org/json/JSONException
    //   345	351	823	org/json/JSONException
    //   351	401	823	org/json/JSONException
    //   408	414	823	org/json/JSONException
    //   414	431	823	org/json/JSONException
    //   438	444	823	org/json/JSONException
    //   444	461	823	org/json/JSONException
    //   468	474	823	org/json/JSONException
    //   474	491	823	org/json/JSONException
    //   498	504	823	org/json/JSONException
    //   504	521	823	org/json/JSONException
    //   528	534	823	org/json/JSONException
    //   534	563	823	org/json/JSONException
    //   570	576	823	org/json/JSONException
    //   576	593	823	org/json/JSONException
    //   600	606	823	org/json/JSONException
    //   606	675	823	org/json/JSONException
    //   683	689	823	org/json/JSONException
    //   692	709	823	org/json/JSONException
    //   716	722	823	org/json/JSONException
    //   722	761	823	org/json/JSONException
    //   761	816	823	org/json/JSONException
  }
}

/* Location:           C:\Users\86186\Downloads\反编译工具包\01_反编译工具包\dex2jar-0.0.9.15\dex2jar-0.0.9.15\classes_dex2jar.jar
 * Qualified Name:     com.baidu.mobstat.bu
 * JD-Core Version:    0.6.2
 */